leap/__init__.py
leap/__main__.py
leap/codec.py
leap/packet.py
leap/helpers/__init__.py
leap/helpers/explore.py
leap/helpers/itemData.py
leap/helpers/protocolKey.py
leap/helpers/typeHelper.py
leap/helpers/verify.py
leap_protocol-1.0.1.dist-info/LICENSE
leap_protocol-1.0.1.dist-info/METADATA
leap_protocol-1.0.1.dist-info/WHEEL
leap_protocol-1.0.1.dist-info/top_level.txt
leap_protocol-1.0.1.dist-info/RECORD
