Metadata-Version: 2.1
Name: leap-protocol
Version: 1.0.1
Summary: Legible Encoding for Addressable Packets
Home-page: https://github.com/leap-protocol/leap-py
Author: Hoani Bryson
Author-email: hoani.bryson@gmail.com
License: UNKNOWN
Platform: UNKNOWN
Classifier: Programming Language :: Python :: 3
Classifier: License :: OSI Approved :: MIT License
Classifier: Operating System :: OS Independent
Requires-Python: >=3.6
Requires-Dist: toml
